{
	"status": "success",
	"data": {
		"title": "树和豆芽的故事",
		"pubtime": "2018/11/16 14:56",
		"mood": "&#xe64f;",
		"weather": "&#xe60d;",
		"id": "4789155363",
		"content": "<p>站在小舍的窗前，望去夜的武汉，繁华、璀璨，但是热闹的背后隐约散发着悲伤的气息。这个将近囚困我两年的城，对我来说还是那么遥远，那么陌生，不管我怎么努力，还是隔着一段距离，我想或许是我的心不在这儿吧。</p><p>灯火阑珊处，只影蹒跚，道不尽过往。回首，重楼不见，那年的烟雨柳巷早已破败不堪，而我们的故事却一直未结束。谁也不知道多年以后的我会重温旧事，且将其写进作品里，她不知道，我也不知道。人生就是如此奇妙，谁也无法预知未来会发生什么。</p><p>我与她认识是在那一年的夏天，结缘则在上一世，那一年她十五岁，可爱甜美，清丽脱俗，散发着少女该有的味道。在那个纯洁的年代，在那个天真的年纪，我们对一切都充满了好奇。于是，开始了青涩年纪懵懂的爱，但也是最真诚最纯洁的爱。但这样的美好并没有持续好久，便遇到了考验——在那个年代，在那个以学习为主的年龄，我们受到了父母，亲戚，老师等的阻碍。我知道此种状况下爱她是一场背离世俗人的孤独归宿，这是一场不被允许且不被祝福的爱，这是一场禁恋，但我不悔有那么一次。</p><p>她，叫小洁，如今已二十了吧，但我们已好久不见了，关于她的记忆一直停留在她十五岁那年。十五岁，一个如花的年纪，而她无疑是那年在我生命中开得最灿烂的花。我原以为把她放在风中更美，时间一长，我发现我错了，只要把她放在风里，风便可撩动我的心弦。如果说还有什么东西能一下子引起我的注意的话，那就是关于她的消息。</p><p>人生若只如初见，何事秋风悲画扇。一切的美好记忆便可在那一刻永恒，可往往事实不是如此的。终有一天我们会明白，即使钟表上的时针或秒针坏了，可时间还是在流逝，它仍然在不断地抽空你的能量，让你不断地衰老， 直至油尽灯枯。那时，再回首往事，真的只是人生若只如初见。希望这一生，哦不，永远都停留在那一刻。</p><p>从挥汗如雨的盛夏一直到树顶渐渐稀疏的初冬，我一直思念着她，这些年来一直如此，似乎这已成了一种习惯。当我人生第一次真正爱的时候，却爱上了一个不该爱的女孩。可我不后悔，那年我爱的真诚，爱的单纯，即使在那个不被允许的环境下剥夺了我的幸福，但那样的经历是幸福的。</p><p>我一直把爱情想象为一次旅行，它的结速就像一个人再次回到自我一样。激情地去爱一个人，常常是一个与自己非常不相像的人，价值就在于它把你的自我带入一个陌生的地域去旅行，或许，那才是真正的我。如果说对那年有所抱怨的话，我想是我没有完全激情地去爱她吧。曾经的山盟海誓，在那个年代，那个环境下变得脆弱不堪，而我们也成了牺牲者的一人。</p>"
	}
}